texttoimage/__init__.py
texttoimage_Jeffrey_Hu-0.0.1.dist-info/LICENSE
texttoimage_Jeffrey_Hu-0.0.1.dist-info/METADATA
texttoimage_Jeffrey_Hu-0.0.1.dist-info/WHEEL
texttoimage_Jeffrey_Hu-0.0.1.dist-info/top_level.txt
texttoimage_Jeffrey_Hu-0.0.1.dist-info/RECORD
