Metadata-Version: 2.1
Name: texttoimage-Jeffrey-Hu
Version: 0.0.1
Summary: A package which can convert text to image.
Home-page: https://github.com/zhiwehu/texttoimage
Author: Jeffrey Hu
Author-email: zhiwehu@gmail.com
License: UNKNOWN
Platform: UNKNOWN
Classifier: Programming Language :: Python :: 3
Classifier: License :: OSI Approved :: MIT License
Classifier: Operating System :: OS Independent
Requires-Python: >=3.6
Requires-Dist: Pillow
